<?xml version="1.0" encoding="UTF-8"?>
<!DOCTYPE plist PUBLIC "-//Apple//DTD PLIST 1.0//EN" "http://www.apple.com/DTDs/PropertyList-1.0.dtd">
<plist version="1.0">
<dict>
	<key>BGTaskSchedulerPermittedIdentifiers</key>
	<array>
		<string>com.google.home.healthcheck</string>
	</array>
	<key>BreakpadProduct</key>
	<string>Google_Cast_iOS</string>
	<key>BuildMachineOSBuild</key>
	<string>24C101</string>
	<key>CADisableMinimumFrameDurationOnPhone</key>
	<true/>
	<key>CFBundleDevelopmentRegion</key>
	<string>en</string>
	<key>CFBundleDisplayName</key>
	<string>Google Home</string>
	<key>CFBundleExecutable</key>
	<string>Home</string>
	<key>CFBundleIcons</key>
	<dict>
		<key>CFBundlePrimaryIcon</key>
		<dict>
			<key>CFBundleIconFiles</key>
			<array>
				<string>logo_google_home_color60x60</string>
			</array>
			<key>CFBundleIconName</key>
			<string>logo_google_home_color</string>
		</dict>
	</dict>
	<key>CFBundleIcons~ipad</key>
	<dict>
		<key>CFBundlePrimaryIcon</key>
		<dict>
			<key>CFBundleIconFiles</key>
			<array>
				<string>logo_google_home_color60x60</string>
				<string>logo_google_home_color76x76</string>
			</array>
			<key>CFBundleIconName</key>
			<string>logo_google_home_color</string>
		</dict>
	</dict>
	<key>CFBundleIdentifier</key>
	<string>com.google.Chromecast</string>
	<key>CFBundleInfoDictionaryVersion</key>
	<string>6.0</string>
	<key>CFBundleName</key>
	<string>Google Home</string>
	<key>CFBundlePackageType</key>
	<string>APPL</string>
	<key>CFBundleShortVersionString</key>
	<string>3.36.56</string>
	<key>CFBundleSupportedPlatforms</key>
	<array>
		<string>iPhoneOS</string>
	</array>
	<key>CFBundleURLTypes</key>
	<array>
		<dict>
			<key>CFBundleURLName</key>
			<string>com.google.Chromecast</string>
			<key>CFBundleURLSchemes</key>
			<array>
				<string>chromecast</string>
				<string>googlehome</string>
			</array>
		</dict>
		<dict>
			<key>CFBundleURLSchemes</key>
			<array>
				<string>chromecast-la</string>
			</array>
		</dict>
		<dict>
			<key>CFBundleURLSchemes</key>
			<array>
				<string>com.google.sso.498579633514-hhlrn8mcjv1427j0s19dgfoe5cqaba4l</string>
			</array>
		</dict>
	</array>
	<key>CFBundleVersion</key>
	<string>3.36.56.16</string>
	<key>DTAppStoreToolsBuild</key>
	<string>16F3</string>
	<key>DTCompiler</key>
	<string>com.apple.compilers.llvm.clang.1_0</string>
	<key>DTPlatformBuild</key>
	<string>22E235</string>
	<key>DTPlatformName</key>
	<string>iphoneos</string>
	<key>DTPlatformVersion</key>
	<string>18.4</string>
	<key>DTSDKBuild</key>
	<string>22E235</string>
	<key>DTSDKName</key>
	<string>iphoneos18.4</string>
	<key>DTXcode</key>
	<string>1630</string>
	<key>DTXcodeBuild</key>
	<string>16E140</string>
	<key>GIDClientID</key>
	<string></string>
	<key>GIDTeamID</key>
	<string>EQHXZ8M8AV</string>
	<key>ITSAppUsesNonExemptEncryption</key>
	<true/>
	<key>ITSEncryptionExportComplianceCode</key>
	<string>4345268e-e3d4-4723-8cbc-6a5fcc1afe67</string>
	<key>LSApplicationQueriesSchemes</key>
	<array>
		<string>spotify</string>
		<string>nflx</string>
		<string>disneyplus</string>
		<string>hulu</string>
		<string>siriusxm</string>
		<string>pandora</string>
		<string>googlechrome</string>
		<string>googlephotos-la</string>
		<string>googleassistant</string>
		<string>comgoogleprimer</string>
		<string>comgooglepublisherapp</string>
		<string>deezer</string>
		<string>googlemybusiness</string>
		<string>googleshoppingex</string>
		<string>iheartradio</string>
		<string>instagram</string>
		<string>pandorav2</string>
		<string>photoscan</string>
		<string>streetview</string>
		<string>tunein</string>
		<string>vnd.youtube.tv</string>
		<string>googletasks</string>
		<string>hue2</string>
		<string>nestmobile</string>
		<string>sonos</string>
		<string>SmartThings</string>
		<string>roku</string>
		<string>tuyasmart</string>
		<string>smartlife</string>
		<string>mihome</string>
		<string>smartglass</string>
		<string>wyze</string>
		<string>kasasmarthome</string>
		<string>lgsmartthinq</string>
		<string>tileapp</string>
		<string>iRobotHome</string>
		<string>arlo</string>
		<string>geeni</string>
		<string>ikea</string>
		<string>nuki</string>
		<string>adtpulse</string>
		<string>MiLamp</string>
		<string>smartcast</string>
		<string>wx6f68a0e1253cd6e3</string>
		<string>ecobee</string>
		<string>com.google.duo</string>
		<string>slingtv</string>
		<string>com.google.fit</string>
	</array>
	<key>LSRequiresIPhoneOS</key>
	<true/>
	<key>MinimumOSVersion</key>
	<string>16.1</string>
	<key>NSAppTransportSecurity</key>
	<dict>
		<key>NSAllowsLocalNetworking</key>
		<true/>
		<key>NSExceptionDomains</key>
		<dict>
			<key>on.here</key>
			<dict>
				<key>NSExceptionAllowsInsecureHTTPLoads</key>
				<true/>
				<key>NSIncludesSubdomains</key>
				<false/>
			</dict>
			<key>onhub.here</key>
			<dict>
				<key>NSExceptionAllowsInsecureHTTPLoads</key>
				<true/>
				<key>NSIncludesSubdomains</key>
				<false/>
			</dict>
		</dict>
		<key>NSPinnedDomains</key>
		<dict>
			<key>google.com</key>
			<dict>
				<key>NSIncludesSubdomains</key>
				<true/>
				<key>NSPinnedCAIdentities</key>
				<array>
					<dict>
						<key>SPKI-SHA256-BASE64</key>
						<string>I/Lt/z7ekCWanjD0Cvj5EqXls2lOaThEA0H2Bg4BT/o=</string>
					</dict>
					<dict>
						<key>SPKI-SHA256-BASE64</key>
						<string>8ca6Zwz8iOTfUpc8rkIPCgid1HQUT+WAbEIAZOFZEik=</string>
					</dict>
					<dict>
						<key>SPKI-SHA256-BASE64</key>
						<string>Fe7TOVlLME+M+Ee0dzcdjW/sYfTbKwGvWJ58U7Ncrkw=</string>
					</dict>
					<dict>
						<key>SPKI-SHA256-BASE64</key>
						<string>r/mIkG3eEpVdm+u/ko/cwxzOMo1bk4TyHIlByibiA5E=</string>
					</dict>
					<dict>
						<key>SPKI-SHA256-BASE64</key>
						<string>i7WTqTvh0OioIruIfFR4kMPnBqrS2rdiVPl/s2uC/CY=</string>
					</dict>
					<dict>
						<key>SPKI-SHA256-BASE64</key>
						<string>uUwZgwDOxcBXrQcntwu+kYFpkiVkOaezL0WYEZ3anJc=</string>
					</dict>
					<dict>
						<key>SPKI-SHA256-BASE64</key>
						<string>WoiWRyIOVNa9ihaBciRSC7XHjliYS9VwUGOIud4PB18=</string>
					</dict>
					<dict>
						<key>SPKI-SHA256-BASE64</key>
						<string>Wd8xe/qfTwq3ylFNd3IpaqLHZbh2ZNCLluVzmeNkcpw=</string>
					</dict>
					<dict>
						<key>SPKI-SHA256-BASE64</key>
						<string>K87oWBWM9UZfyddvDfoxL+8lpNyoUB2ptGtn0fv6G2Q=</string>
					</dict>
					<dict>
						<key>SPKI-SHA256-BASE64</key>
						<string>cGuxAXyFXFkWm61cF4HPWX8S0srS9j0aSqN0k4AP+4A=</string>
					</dict>
					<dict>
						<key>SPKI-SHA256-BASE64</key>
						<string>fg6tdrtoGdwvVFEahDVPboswe53YIFjqbABPAdndpd8=</string>
					</dict>
					<dict>
						<key>SPKI-SHA256-BASE64</key>
						<string>aCdH+LpiG4fN07wpXtXKvOciocDANj0daLOJKNJ4fx4=</string>
					</dict>
					<dict>
						<key>SPKI-SHA256-BASE64</key>
						<string>Ko8tivDrEjiY90yGasP6ZpBU4jwXvHqVvQI0GS3GNdA=</string>
					</dict>
					<dict>
						<key>SPKI-SHA256-BASE64</key>
						<string>gI1os/q0iEpflxrOfRBVDXqVoWN3Tz7Dav/7IT++THQ=</string>
					</dict>
					<dict>
						<key>SPKI-SHA256-BASE64</key>
						<string>FfFKxFycfaIz00eRZOgTf+Ne4POK6FgYPwhBDqgqxLQ=</string>
					</dict>
					<dict>
						<key>SPKI-SHA256-BASE64</key>
						<string>VjLZe/p3W/PJnd6lL8JVNBCGQBZynFLdZSTIqcO0SJ8=</string>
					</dict>
					<dict>
						<key>SPKI-SHA256-BASE64</key>
						<string>vRU+17BDT2iGsXvOi76E7TQMcTLXAqj0+jGPdW7L1vM=</string>
					</dict>
					<dict>
						<key>SPKI-SHA256-BASE64</key>
						<string>AG1751Vd2CAmRCxPGieoDomhmJy4ezREjtIZTBgZbV4=</string>
					</dict>
					<dict>
						<key>SPKI-SHA256-BASE64</key>
						<string>58qRu/uxh4gFezqAcERupSkRYBlBAvfcw7mEjGPLnNU=</string>
					</dict>
					<dict>
						<key>SPKI-SHA256-BASE64</key>
						<string>grX4Ta9HpZx6tSHkmCrvpApTQGo67CYDnvprLg5yRME=</string>
					</dict>
					<dict>
						<key>SPKI-SHA256-BASE64</key>
						<string>ICGRfpgmOUXIWcQ/HXPLQTkFPEFPoDyjvH7ohhQpjzs=</string>
					</dict>
					<dict>
						<key>SPKI-SHA256-BASE64</key>
						<string>x4QzPSC810K5/cMjb05Qm4k3Bw5zBn4lTdO/nEW/Td4=</string>
					</dict>
					<dict>
						<key>SPKI-SHA256-BASE64</key>
						<string>hxqRlPTu1bMS/0DITB1SSu0vd4u/8l8TjPgfaAp63Gc=</string>
					</dict>
					<dict>
						<key>SPKI-SHA256-BASE64</key>
						<string>Vfd95BwDeSQo+NUYxVEEIlvkOlWY2SalKK1lPhzOx78=</string>
					</dict>
					<dict>
						<key>SPKI-SHA256-BASE64</key>
						<string>QXnt2YHvdHR3tJYmQIr0Paosp6t/nggsEGD4QJZ3Q0g=</string>
					</dict>
					<dict>
						<key>SPKI-SHA256-BASE64</key>
						<string>mEflZT5enoR1FuXLgYYGqnVEoZvmf9c2bVBpiOjYQ0c=</string>
					</dict>
					<dict>
						<key>SPKI-SHA256-BASE64</key>
						<string>CLOmM1/OXvSPjw5UOYbAf9GKOxImEp9hhku9W90fHMk=</string>
					</dict>
				</array>
			</dict>
			<key>googleapis.com</key>
			<dict>
				<key>NSIncludesSubdomains</key>
				<true/>
				<key>NSPinnedCAIdentities</key>
				<array>
					<dict>
						<key>SPKI-SHA256-BASE64</key>
						<string>I/Lt/z7ekCWanjD0Cvj5EqXls2lOaThEA0H2Bg4BT/o=</string>
					</dict>
					<dict>
						<key>SPKI-SHA256-BASE64</key>
						<string>8ca6Zwz8iOTfUpc8rkIPCgid1HQUT+WAbEIAZOFZEik=</string>
					</dict>
					<dict>
						<key>SPKI-SHA256-BASE64</key>
						<string>Fe7TOVlLME+M+Ee0dzcdjW/sYfTbKwGvWJ58U7Ncrkw=</string>
					</dict>
					<dict>
						<key>SPKI-SHA256-BASE64</key>
						<string>r/mIkG3eEpVdm+u/ko/cwxzOMo1bk4TyHIlByibiA5E=</string>
					</dict>
					<dict>
						<key>SPKI-SHA256-BASE64</key>
						<string>i7WTqTvh0OioIruIfFR4kMPnBqrS2rdiVPl/s2uC/CY=</string>
					</dict>
					<dict>
						<key>SPKI-SHA256-BASE64</key>
						<string>uUwZgwDOxcBXrQcntwu+kYFpkiVkOaezL0WYEZ3anJc=</string>
					</dict>
					<dict>
						<key>SPKI-SHA256-BASE64</key>
						<string>WoiWRyIOVNa9ihaBciRSC7XHjliYS9VwUGOIud4PB18=</string>
					</dict>
					<dict>
						<key>SPKI-SHA256-BASE64</key>
						<string>Wd8xe/qfTwq3ylFNd3IpaqLHZbh2ZNCLluVzmeNkcpw=</string>
					</dict>
					<dict>
						<key>SPKI-SHA256-BASE64</key>
						<string>K87oWBWM9UZfyddvDfoxL+8lpNyoUB2ptGtn0fv6G2Q=</string>
					</dict>
					<dict>
						<key>SPKI-SHA256-BASE64</key>
						<string>cGuxAXyFXFkWm61cF4HPWX8S0srS9j0aSqN0k4AP+4A=</string>
					</dict>
					<dict>
						<key>SPKI-SHA256-BASE64</key>
						<string>fg6tdrtoGdwvVFEahDVPboswe53YIFjqbABPAdndpd8=</string>
					</dict>
					<dict>
						<key>SPKI-SHA256-BASE64</key>
						<string>aCdH+LpiG4fN07wpXtXKvOciocDANj0daLOJKNJ4fx4=</string>
					</dict>
					<dict>
						<key>SPKI-SHA256-BASE64</key>
						<string>Ko8tivDrEjiY90yGasP6ZpBU4jwXvHqVvQI0GS3GNdA=</string>
					</dict>
					<dict>
						<key>SPKI-SHA256-BASE64</key>
						<string>gI1os/q0iEpflxrOfRBVDXqVoWN3Tz7Dav/7IT++THQ=</string>
					</dict>
					<dict>
						<key>SPKI-SHA256-BASE64</key>
						<string>FfFKxFycfaIz00eRZOgTf+Ne4POK6FgYPwhBDqgqxLQ=</string>
					</dict>
					<dict>
						<key>SPKI-SHA256-BASE64</key>
						<string>VjLZe/p3W/PJnd6lL8JVNBCGQBZynFLdZSTIqcO0SJ8=</string>
					</dict>
					<dict>
						<key>SPKI-SHA256-BASE64</key>
						<string>vRU+17BDT2iGsXvOi76E7TQMcTLXAqj0+jGPdW7L1vM=</string>
					</dict>
					<dict>
						<key>SPKI-SHA256-BASE64</key>
						<string>AG1751Vd2CAmRCxPGieoDomhmJy4ezREjtIZTBgZbV4=</string>
					</dict>
					<dict>
						<key>SPKI-SHA256-BASE64</key>
						<string>58qRu/uxh4gFezqAcERupSkRYBlBAvfcw7mEjGPLnNU=</string>
					</dict>
					<dict>
						<key>SPKI-SHA256-BASE64</key>
						<string>grX4Ta9HpZx6tSHkmCrvpApTQGo67CYDnvprLg5yRME=</string>
					</dict>
					<dict>
						<key>SPKI-SHA256-BASE64</key>
						<string>ICGRfpgmOUXIWcQ/HXPLQTkFPEFPoDyjvH7ohhQpjzs=</string>
					</dict>
					<dict>
						<key>SPKI-SHA256-BASE64</key>
						<string>x4QzPSC810K5/cMjb05Qm4k3Bw5zBn4lTdO/nEW/Td4=</string>
					</dict>
					<dict>
						<key>SPKI-SHA256-BASE64</key>
						<string>hxqRlPTu1bMS/0DITB1SSu0vd4u/8l8TjPgfaAp63Gc=</string>
					</dict>
					<dict>
						<key>SPKI-SHA256-BASE64</key>
						<string>Vfd95BwDeSQo+NUYxVEEIlvkOlWY2SalKK1lPhzOx78=</string>
					</dict>
					<dict>
						<key>SPKI-SHA256-BASE64</key>
						<string>QXnt2YHvdHR3tJYmQIr0Paosp6t/nggsEGD4QJZ3Q0g=</string>
					</dict>
					<dict>
						<key>SPKI-SHA256-BASE64</key>
						<string>mEflZT5enoR1FuXLgYYGqnVEoZvmf9c2bVBpiOjYQ0c=</string>
					</dict>
					<dict>
						<key>SPKI-SHA256-BASE64</key>
						<string>CLOmM1/OXvSPjw5UOYbAf9GKOxImEp9hhku9W90fHMk=</string>
					</dict>
				</array>
			</dict>
		</dict>
	</dict>
	<key>NSAppleMusicUsageDescription</key>
	<string>Your Assistant needs to access your music library to play music for you.</string>
	<key>NSBluetoothAlwaysUsageDescription</key>
	<string>Bluetooth is needed to discover and set up nearby devices.</string>
	<key>NSBluetoothPeripheralUsageDescription</key>
	<string>Bluetooth is used to detect nearby devices.</string>
	<key>NSBonjourServices</key>
	<array>
		<string>_matter._tcp</string>
		<string>_matterc._udp</string>
		<string>_matterd._udp</string>
	</array>
	<key>NSCalendarsUsageDescription</key>
	<string>Your Assistant needs to access your calendar to show you all your events in one place.</string>
	<key>NSCameraUsageDescription</key>
	<string>This allows you to scan QR codes, set up and scan credit cards, and set up Face Match on your Google Nest device.</string>
	<key>NSContactsUsageDescription</key>
	<string>This will allow you to easily invite people from your contacts without retyping their email address.</string>
	<key>NSFaceIDUsageDescription</key>
	<string>Google Home needs permission to use your Face ID to sign in your Google account to Chromecast.</string>
	<key>NSLocalNetworkUsageDescription</key>
	<string>The app uses the local network to set up and control your connected devices.</string>
	<key>NSLocationAlwaysAndWhenInUseUsageDescription</key>
	<string>The Home app needs one-time or in-app location access to set up and manage nearby devices. Features that use presence detection, like Home &amp; Away Routines, will only work when location access is always allowed.</string>
	<key>NSLocationAlwaysUsageDescription</key>
	<string>The Home app needs one-time or in-app location access to set up and manage nearby devices. Features that use presence detection, like Home &amp; Away Routines, will only work when location access is always allowed.</string>
	<key>NSLocationWhenInUseUsageDescription</key>
	<string>Location access is needed to set up and manage nearby devices.</string>
	<key>NSMicrophoneUsageDescription</key>
	<string>The microphone can be used to speak with the Assistant or for two way audio on supported devices.</string>
	<key>NSPhotoLibraryUsageDescription</key>
	<string>Google Home needs permission to use your camera in order to scan your card.</string>
	<key>UIBackgroundModes</key>
	<array>
		<string>bluetooth-central</string>
		<string>bluetooth-peripheral</string>
		<string>remote-notification</string>
		<string>audio</string>
		<string>fetch</string>
	</array>
	<key>UIDeviceFamily</key>
	<array>
		<integer>1</integer>
		<integer>2</integer>
	</array>
	<key>UILaunchStoryboardName</key>
	<string>LaunchScreen</string>
	<key>UIPrerenderedIcon</key>
	<true/>
	<key>UIRequiredDeviceCapabilities</key>
	<array>
		<string>arm64</string>
	</array>
	<key>UIRequiresFullScreen</key>
	<true/>
	<key>UIRequiresPersistentWiFi</key>
	<true/>
	<key>UIStatusBarStyle</key>
	<string>UIStatusBarStyleDefault</string>
	<key>UISupportedInterfaceOrientations</key>
	<array>
		<string>UIInterfaceOrientationPortrait</string>
		<string>UIInterfaceOrientationLandscapeLeft</string>
		<string>UIInterfaceOrientationLandscapeRight</string>
	</array>
	<key>UISupportedInterfaceOrientations~ipad</key>
	<array>
		<string>UIInterfaceOrientationPortrait</string>
		<string>UIInterfaceOrientationPortraitUpsideDown</string>
		<string>UIInterfaceOrientationLandscapeLeft</string>
		<string>UIInterfaceOrientationLandscapeRight</string>
	</array>
</dict>
</plist>
