<?xml version="1.0" encoding="UTF-8"?>
<!DOCTYPE plist PUBLIC "-//Apple//DTD PLIST 1.0//EN" "http://www.apple.com/DTDs/PropertyList-1.0.dtd">
<plist version="1.0">
<dict>
	<key>BGTaskSchedulerPermittedIdentifiers</key>
	<array>
		<string>com.microsoft.identity-broker.operation.refresh</string>
	</array>
	<key>BuildMachineOSBuild</key>
	<string>24C101</string>
	<key>CFBundleDevelopmentRegion</key>
	<string>English</string>
	<key>CFBundleDisplayName</key>
	<string>Authenticator</string>
	<key>CFBundleExecutable</key>
	<string>Microsoft Authenticator</string>
	<key>CFBundleIcons</key>
	<dict>
		<key>CFBundlePrimaryIcon</key>
		<dict>
			<key>CFBundleIconFiles</key>
			<array>
				<string>AppIcon60x60</string>
			</array>
			<key>CFBundleIconName</key>
			<string>AppIcon</string>
		</dict>
	</dict>
	<key>CFBundleIcons~ipad</key>
	<dict>
		<key>CFBundlePrimaryIcon</key>
		<dict>
			<key>CFBundleIconFiles</key>
			<array>
				<string>AppIcon60x60</string>
				<string>AppIcon76x76</string>
			</array>
			<key>CFBundleIconName</key>
			<string>AppIcon</string>
		</dict>
	</dict>
	<key>CFBundleIdentifier</key>
	<string>com.microsoft.azureauthenticator</string>
	<key>CFBundleInfoDictionaryVersion</key>
	<string>6.0</string>
	<key>CFBundleName</key>
	<string>Microsoft Authenticator</string>
	<key>CFBundlePackageType</key>
	<string>APPL</string>
	<key>CFBundleShortVersionString</key>
	<string>6.8.23</string>
	<key>CFBundleSignature</key>
	<string>????</string>
	<key>CFBundleSupportedPlatforms</key>
	<array>
		<string>iPhoneOS</string>
	</array>
	<key>CFBundleURLTypes</key>
	<array>
		<dict>
			<key>CFBundleTypeRole</key>
			<string>Editor</string>
			<key>CFBundleURLName</key>
			<string>com.microsoft.azureauthenticator</string>
			<key>CFBundleURLSchemes</key>
			<array>
				<string>brooklyn-extension</string>
				<string>msauth</string>
				<string>ms-log-azureauthenticator</string>
				<string>microsoft-authenticator</string>
				<string>otpauth</string>
				<string>msauthv2</string>
				<string>msauthv3</string>
				<string>openid</string>
				<string>openid-vc</string>
				<string>vcclient</string>
				<string>msa-devicekey-share</string>
				<string>mspasskey</string>
			</array>
		</dict>
	</array>
	<key>CFBundleVersion</key>
	<string>5</string>
	<key>DTAppStoreToolsBuild</key>
	<string>16C7015</string>
	<key>DTCompiler</key>
	<string>com.apple.compilers.llvm.clang.1_0</string>
	<key>DTPlatformBuild</key>
	<string>22A3362</string>
	<key>DTPlatformName</key>
	<string>iphoneos</string>
	<key>DTPlatformVersion</key>
	<string>18.0</string>
	<key>DTSDKBuild</key>
	<string>22A3362</string>
	<key>DTSDKName</key>
	<string>iphoneos18.0</string>
	<key>DTXcode</key>
	<string>1600</string>
	<key>DTXcodeBuild</key>
	<string>16A242d</string>
	<key>LSApplicationQueriesSchemes</key>
	<array>
		<string>msauth</string>
		<string>msauthv2</string>
		<string>msauthv3</string>
		<string>googlechrome</string>
	</array>
	<key>LSRequiresIPhoneOS</key>
	<true/>
	<key>MinimumOSVersion</key>
	<string>16.0</string>
	<key>NSAppTransportSecurity</key>
	<dict>
		<key>NSAllowsArbitraryLoadsInWebContent</key>
		<true/>
	</dict>
	<key>NSCameraUsageDescription</key>
	<string>May be needed to scan QR code to add a new account</string>
	<key>NSFaceIDUsageDescription</key>
	<string>Face ID will be used to authenticate your identity with Microsoft services.</string>
	<key>NSLocationAlwaysAndWhenInUseUsageDescription</key>
	<string>Your company requires you to share your location to access sensitive data.​ Always allow access to avoid future prompts.</string>
	<key>NSLocationWhenInUseUsageDescription</key>
	<string>Your company requires you to share your location to access sensitive data.​ Always allow access to avoid future prompts.</string>
	<key>NSMicrophoneUsageDescription</key>
	<string>This application only requests for microphone permissions when performing voice authentication</string>
	<key>NSPhotoLibraryAddUsageDescription</key>
	<string>This application never requests access to the user's photo library. The app has access only to screenshots that the user chooses to upload when reporting an issue or sending feedback.</string>
	<key>NSPhotoLibraryUsageDescription</key>
	<string>This application never requests access to the user's photo library. The app has access only to screenshots that the user chooses to upload when reporting an issue or sending feedback.</string>
	<key>UIBackgroundModes</key>
	<array>
		<string>fetch</string>
		<string>processing</string>
		<string>remote-notification</string>
	</array>
	<key>UIDeviceFamily</key>
	<array>
		<integer>1</integer>
		<integer>2</integer>
	</array>
	<key>UILaunchStoryboardName</key>
	<string>Storyboard</string>
	<key>UIMainStoryboardFile</key>
	<string>Storyboard</string>
	<key>UIMainStoryboardFile~ipad</key>
	<string>Storyboard</string>
	<key>UIRequiredDeviceCapabilities</key>
	<array>
		<string>arm64</string>
	</array>
	<key>UISupportedInterfaceOrientations</key>
	<array>
		<string>UIInterfaceOrientationPortrait</string>
		<string>UIInterfaceOrientationPortraitUpsideDown</string>
		<string>UIInterfaceOrientationLandscapeLeft</string>
		<string>UIInterfaceOrientationLandscapeRight</string>
	</array>
	<key>UISupportedInterfaceOrientations~ipad</key>
	<array>
		<string>UIInterfaceOrientationPortrait</string>
		<string>UIInterfaceOrientationPortraitUpsideDown</string>
		<string>UIInterfaceOrientationLandscapeLeft</string>
		<string>UIInterfaceOrientationLandscapeRight</string>
	</array>
	<key>UIUserInterfaceStyle</key>
	<string>Light</string>
	<key>UIViewControllerBasedStatusBarAppearance</key>
	<true/>
	<key>UTImportedTypeDeclarations</key>
	<array>
		<dict>
			<key>UTTypeConformsTo</key>
			<array>
				<string>public.data</string>
				<string>public.content</string>
			</array>
			<key>UTTypeIdentifier</key>
			<string>com.microsoft.azureauthenticator.did.import</string>
			<key>UTTypeTagSpecification</key>
			<dict>
				<key>public.filename-extension</key>
				<array>
					<string>jwt</string>
				</array>
			</dict>
		</dict>
	</array>
</dict>
</plist>
